setup.py
blended/__init__.py
blendedUx_staging.egg-info/PKG-INFO
blendedUx_staging.egg-info/SOURCES.txt
blendedUx_staging.egg-info/dependency_links.txt
blendedUx_staging.egg-info/entry_points.txt
blendedUx_staging.egg-info/requires.txt
blendedUx_staging.egg-info/top_level.txt
blended/blended_flask/__init__.py
blended/blended_flask/app.py
blended/blended_flask/functions.py
blended/blended_flask/settings.py
blended/blended_flask/utils.py
blended/blended_hostlib/__init__.py
blended/blended_hostlib/initializer.py
blended/blended_hostlib/tests.py
blended/blended_hostlib/transform_image.py
blended/blended_hostlib/backend/__init__.py
blended/blended_hostlib/backend/backend.py
blended/blended_hostlib/backend/intermediary.py
blended/blended_hostlib/backend/settings.py
blended/blended_hostlib/controller/__init__.py
blended/blended_hostlib/controller/controller.py
blended/blended_hostlib/exceptions/__init__.py
blended/blended_hostlib/exceptions/exceptions.py
blended/blended_hostlib/functions/__init__.py
blended/blended_hostlib/functions/functions.py
blended/blended_hostlib/network/__init__.py
blended/blended_hostlib/network/network.py
blended/blended_hostlib/network/settings.py
blended/blended_hostlib/swagger_client/__init__.py
blended/blended_hostlib/swagger_client/api_client.py
blended/blended_hostlib/swagger_client/configuration.py
blended/blended_hostlib/swagger_client/rest.py
blended/blended_hostlib/swagger_client/apis/__init__.py
blended/blended_hostlib/swagger_client/apis/accounts_api.py
blended/blended_hostlib/swagger_client/apis/packages_api.py
blended/blended_hostlib/swagger_client/models/__init__.py
blended/blended_hostlib/swagger_client/models/account.py
blended/blended_hostlib/swagger_client/models/account_invite_pending.py
blended/blended_hostlib/swagger_client/models/account_invites_pending_list.py
blended/blended_hostlib/swagger_client/models/accounts.py
blended/blended_hostlib/swagger_client/models/acquisition.py
blended/blended_hostlib/swagger_client/models/acquisition_response.py
blended/blended_hostlib/swagger_client/models/acquisition_response_data.py
blended/blended_hostlib/swagger_client/models/activationchallenge.py
blended/blended_hostlib/swagger_client/models/active_account.py
