Metadata-Version: 2.1
Name: blendedUx-staging
Version: 0.0.1
Summary: test_package_for_blendedUx
Author: Sunny Prakash
Author-email: <sprakash@cognam.com>
